setup.py
src/digimat/__init__.py
src/digimat.fielddevice.egg-info/PKG-INFO
src/digimat.fielddevice.egg-info/SOURCES.txt
src/digimat.fielddevice.egg-info/dependency_links.txt
src/digimat.fielddevice.egg-info/namespace_packages.txt
src/digimat.fielddevice.egg-info/not-zip-safe
src/digimat.fielddevice.egg-info/requires.txt
src/digimat.fielddevice.egg-info/top_level.txt
src/digimat/fielddevice/__init__.py
src/digimat/fielddevice/device.py
src/digimat/fielddevice/vio.py