Metadata-Version: 1.0
Name: digimat.fielddevice
Version: 0.1.0
Summary: Digimat RWS FieldDevice
Home-page: UNKNOWN
Author: Frederic Hess
Author-email: fhess@splust.ch
License: PSF
Platform: UNKNOWN
